biobb_dna/__init__.py
biobb_dna/py.typed
biobb_dna/backbone/__init__.py
biobb_dna/backbone/bipopulations.py
biobb_dna/backbone/canonicalag.py
biobb_dna/backbone/puckering.py
biobb_dna/curvesplus/__init__.py
biobb_dna/curvesplus/biobb_canal.py
biobb_dna/curvesplus/biobb_canion.py
biobb_dna/curvesplus/biobb_curves.py
biobb_dna/curvesplus/canal_unzip.py
biobb_dna/dna/__init__.py
biobb_dna/dna/dna_averages.py
biobb_dna/dna/dna_bimodality.py
biobb_dna/dna/dna_timeseries.py
biobb_dna/dna/dna_timeseries_unzip.py
biobb_dna/interbp_correlations/__init__.py
biobb_dna/interbp_correlations/interbpcorr.py
biobb_dna/interbp_correlations/interhpcorr.py
biobb_dna/interbp_correlations/interseqcorr.py
biobb_dna/intrabp_correlations/__init__.py
biobb_dna/intrabp_correlations/intrabpcorr.py
biobb_dna/intrabp_correlations/intrahpcorr.py
biobb_dna/intrabp_correlations/intraseqcorr.py
biobb_dna/stiffness/__init__.py
biobb_dna/stiffness/average_stiffness.py
biobb_dna/stiffness/basepair_stiffness.py
biobb_dna/test/__init__.py
biobb_dna/utils/__init__.py
biobb_dna/utils/common.py
biobb_dna/utils/constants.py
biobb_dna/utils/loader.py
biobb_dna/utils/transform.py
biobb_dna-5.2.0.dist-info/licenses/LICENSE
biobb_dna-5.2.0.dist-info/METADATA
biobb_dna-5.2.0.dist-info/WHEEL
biobb_dna-5.2.0.dist-info/entry_points.txt
biobb_dna-5.2.0.dist-info/top_level.txt
biobb_dna-5.2.0.dist-info/RECORD
