Metadata-Version: 2.4
Name: biobb_dna
Version: 5.2.0
Summary: Biobb_dna is a package composed of different analyses for nucleic acid trajectories.
Home-page: https://github.com/bioexcel/biobb_dna
Author: Biobb developers
Author-email: genis.bayarri@irbbarcelona.com
Project-URL: Documentation, http://biobb-dna.readthedocs.io/en/latest/
Project-URL: Bioexcel, https://bioexcel.eu/
Keywords: Bioinformatics Workflows BioExcel Compatibility
Classifier: Development Status :: 5 - Production/Stable
Classifier: Programming Language :: Python :: 3.10
Classifier: License :: OSI Approved :: Apache Software License
Classifier: Operating System :: MacOS :: MacOS X
Classifier: Operating System :: POSIX
Classifier: Operating System :: Unix
Requires-Python: >=3.10
License-File: LICENSE
Requires-Dist: biobb_common==5.2.0
Requires-Dist: pandas>=1.3.0
Requires-Dist: scikit-learn>=0.24.2
Dynamic: author
Dynamic: author-email
Dynamic: classifier
Dynamic: description
Dynamic: description-content-type
Dynamic: home-page
Dynamic: keywords
Dynamic: license-file
Dynamic: project-url
Dynamic: requires-dist
Dynamic: requires-python
Dynamic: summary
